chessfessor/__init__.py
chessfessor/__main__.py
chessfessor/extractors/__init__.py
chessfessor/extractors/chessdotcom_extractor.py
chessfessor/extractors/lichess_extractor.py
chessfessor-1.0.10.dist-info/LICENSE
chessfessor-1.0.10.dist-info/METADATA
chessfessor-1.0.10.dist-info/WHEEL
chessfessor-1.0.10.dist-info/top_level.txt
chessfessor-1.0.10.dist-info/RECORD
