Metadata-Version: 2.1
Name: chessfessor
Version: 1.0.10
Summary: Extract your chess games data from https://lichess.org and https://chess.com
Home-page: https://github.com/FrequentlyMissedDeadlines/py-chessfessor
Author: FrequentlyMissedDeadlines
Author-email: FrequentlyMissedDeadlines+chessfessor@gmail.com
License: UNKNOWN
Project-URL: Bug Reports, https://github.com/FrequentlyMissedDeadlines/py-chessfessor/issues
Project-URL: Source, https://github.com/FrequentlyMissedDeadlines/py-chessfessor
Platform: UNKNOWN
Classifier: Programming Language :: Python :: 3
Classifier: License :: OSI Approved :: MIT License
Classifier: Operating System :: OS Independent
Classifier: Development Status :: 5 - Production/Stable
Classifier: Intended Audience :: End Users/Desktop
Classifier: Natural Language :: English
Classifier: Topic :: Games/Entertainment :: Board Games
Classifier: Programming Language :: Python :: 3.7
Classifier: Programming Language :: Python :: 3.8
Classifier: Programming Language :: Python :: 3.9
Classifier: Programming Language :: Python :: 3.10
